[{"name": "\u4e07\u6625\u660e", "email": "", "created_at": "2016-03-13T15:56:45", "content": "\u613f\u4e0d\u518d\u590d\u53d1\n\n"}, {"name": "\u6f29\u6da1", "email": "", "created_at": "2016-03-14T01:56:29", "content": "\u611f\u8c22\uff0c\u6211\u4e5f\u5728\u52aa\u529b\u5b9e\u73b0\u8fd9\u4e00\u70b9~\n\n"}, {"name": "\u9ad8\u8f69", "email": "", "created_at": "2016-03-28T07:53:47", "content": "\u770b\u81f3\u603b\u7ed3\u90e8\u5206\uff0c\u9690\u7ea6\u6709\u4e9b\u5fc3\u75bc\uff0c\u611f\u6069\u535a\u4e3b\u7684\u7ec6\u817b\u3002\n\n"}, {"name": "Reorx", "email": "", "created_at": "2016-05-25T05:05:11", "content": "Bless\uff0c\u8eab\u4f53\u662f\u7b2c\u4e00\u8981\u7d27\u7684\uff0c\u4e16\u754c\u4e0a\u8fd8\u6709\u5927\u628a\u6709\u8da3\u7684\u4e8b\u60c5\u7b49\u7740\u6211\u4eec\u53bb\u505a\u5462\u3002\n\n"}, {"name": "\u6f29\u6da1", "email": "", "created_at": "2016-05-25T16:12:37", "content": "\u8c22\u8c22\uff5e\n\n"}]